robust_request/__init__.py
robust_request/requester.py
robust_request/robust_request.py
robust_request/robust_request_.py
robust_request-0.2.1.dist-info/LICENSE
robust_request-0.2.1.dist-info/METADATA
robust_request-0.2.1.dist-info/WHEEL
robust_request-0.2.1.dist-info/top_level.txt
robust_request-0.2.1.dist-info/zip-safe
robust_request-0.2.1.dist-info/RECORD
