Metadata-Version: 2.1
Name: robust-request
Version: 0.2.1
Summary: A more reliable http request.
Home-page: https://github.com/JesseAldridge/robust_request
Author: Jesse Aldridge
Author-email: JesseAldridge@gmail.com
License: MIT
Keywords: http requests
Platform: UNKNOWN
License-File: LICENSE
Requires-Dist: requests
